aug_sfutils/__init__.py
aug_sfutils/config.py
aug_sfutils/contour.py
aug_sfutils/equilibrium.py
aug_sfutils/getlastshot.py
aug_sfutils/journal.py
aug_sfutils/libddc.py
aug_sfutils/manage_ed.py
aug_sfutils/mapeq.py
aug_sfutils/parse_kwargs.py
aug_sfutils/read_imas.py
aug_sfutils/sfh.py
aug_sfutils/sfhmod.py
aug_sfutils/sfmap.py
aug_sfutils/sfobj.py
aug_sfutils/sfread.py
aug_sfutils/shotfile.py
aug_sfutils/str_byt.py
aug_sfutils/time_no_elm.py
aug_sfutils/time_slice.py
aug_sfutils/ww.py
aug_sfutils-0.9.2.dist-info/LICENSE
aug_sfutils-0.9.2.dist-info/METADATA
aug_sfutils-0.9.2.dist-info/WHEEL
aug_sfutils-0.9.2.dist-info/top_level.txt
aug_sfutils-0.9.2.dist-info/RECORD
