Metadata-Version: 2.2
Name: aug_sfutils
Version: 0.9.2
Summary: A utility to read AUG shotfiles
Home-page: https://gitlab.mpcdf.mpg.de/git/aug_sfutils
Author: Giovanni Tardini
Author-email: giovannitardini@yahoo.de
Classifier: Programming Language :: Python :: 3
Classifier: License :: OSI Approved :: MIT License
Classifier: Operating System :: OS Independent
Requires-Python: >=2.6
License-File: LICENSE
